seqrecord_expanded/__init__.py
seqrecord_expanded/_warnings.py
seqrecord_expanded/exceptions.py
seqrecord_expanded/seqrecord.py
seqrecord_expanded/utils.py
seqrecord_expanded-0.2.16.dist-info/METADATA
seqrecord_expanded-0.2.16.dist-info/WHEEL
seqrecord_expanded-0.2.16.dist-info/top_level.txt
seqrecord_expanded-0.2.16.dist-info/RECORD
