Metadata-Version: 2.4
Name: seqrecord_expanded
Version: 0.2.16
Summary: Another SeqRecord class with methods: degenerate seqs, codon positions based on reading frames, etc.
Home-page: https://github.com/carlosp420/seqrecord-expanded
Author: Carlos Peña
Author-email: mycalesis@gmail.com
License: BSD
Classifier: Development Status :: 5 - Production/Stable
Classifier: Programming Language :: Python
Classifier: Programming Language :: Python :: 3.10
Classifier: Programming Language :: Python :: 3.11
Classifier: Programming Language :: Python :: 3.12
Classifier: Topic :: Scientific/Engineering :: Bio-Informatics
Requires-Dist: biopython==1.85
Requires-Dist: degenerate-dna==0.1.2
Dynamic: author
Dynamic: author-email
Dynamic: classifier
Dynamic: description
Dynamic: description-content-type
Dynamic: home-page
Dynamic: license
Dynamic: requires-dist
Dynamic: summary
